gym_vec_env/__init__.py
gym_vec_env/test.py
gym_vec_env-0.0.2.dist-info/METADATA
gym_vec_env-0.0.2.dist-info/RECORD
gym_vec_env-0.0.2.dist-info/WHEEL
gym_vec_env-0.0.2.dist-info/top_level.txt
