Metadata-Version: 2.1
Name: gym-vec-env
Version: 0.0.2
Summary: UNKNOWN
Home-page: https://github.com/nottombrown
Author: Tom Brown
Author-email: nottombrown@gmail.com
License: UNKNOWN
Platform: UNKNOWN
Requires-Dist: gym
